mcp_server/__init__.py
mcp_server/__main__.py
mcp_server/config.py
mcp_server/skill_parameter.py
mcp_server/tool_registry.py
mcp_server/auth/dynamic_auth_middleware.py
mcp_server/auth/fastmcp_extended.py
mcp_server/auth/token_verifier.py
mcp_server/modes/__init__.py
mcp_server/modes/base.py
mcp_server/modes/local.py
mcp_server/modes/remote.py
mcp_server/utils/__init__.py
mcp_server/utils/client.py
mcp_server/utils/context.py
mcp_server/utils/copilot.py
mcp_server/utils/skill.py
mcp_server/utils/tool.py
mcp_server/utils/validation.py
maxai_mcp-0.2.12.dist-info/METADATA
maxai_mcp-0.2.12.dist-info/WHEEL
maxai_mcp-0.2.12.dist-info/entry_points.txt
maxai_mcp-0.2.12.dist-info/top_level.txt
maxai_mcp-0.2.12.dist-info/RECORD
