Metadata-Version: 2.4
Name: maxai-mcp
Version: 0.2.12
Summary: MCP server that connects to Max AI agents
Requires-Python: >=3.10.7
Requires-Dist: answerrocket-client==0.2.78
Requires-Dist: mcp>=1.25.0
Requires-Dist: starlette>=0.49.1
Requires-Dist: starlette-context==0.4.0
